setup.py
gc_prometheus/__init__.py
gc_prometheus/profile.py
gc_prometheus.egg-info/PKG-INFO
gc_prometheus.egg-info/SOURCES.txt
gc_prometheus.egg-info/dependency_links.txt
gc_prometheus.egg-info/requires.txt
gc_prometheus.egg-info/top_level.txt