Metadata-Version: 1.1
Name: gc-prometheus
Version: 0.1.0
Summary: Exports garbage collection metrics for Prometheus.io.
Home-page: http://github.com/korfuri/python-gc-prometheus
Author: Uriel Corfa
Author-email: uriel@corfa.fr
License: Apache
Keywords: python gc monitoring prometheus
Platform: UNKNOWN
Classifier: Development Status :: 4 - Beta
Classifier: Intended Audience :: Developers
Classifier: Intended Audience :: Information Technology
Classifier: Intended Audience :: System Administrators
Classifier: Topic :: System :: Monitoring
Classifier: License :: OSI Approved :: Apache Software License
